demo/cix32_demo.v
// Minimal working x86 core for demonstration
module cix32_demo (
    input wire clk,
    input wire rst_n,
    output reg [31:0] pc,
    output reg [31:0] eax,
    output reg halted
);

    reg [7:0] memory [0:255];
    reg [2:0] state;
    reg [7:0] opcode;
    
    initial begin
        memory[0] = 8'h40;  // INC EAX
        memory[1] = 8'h40;  // INC EAX  
        memory[2] = 8'h48;  // DEC EAX
        memory[3] = 8'h40;  // INC EAX
        memory[4] = 8'hF4;  // HLT
    end
    
    always @(posedge clk or negedge rst_n) begin
        if (!rst_n) begin
            pc <= 32'h0;
            eax <= 32'h0;
            halted <= 1'b0;
            state <= 3'h0;
        end else if (!halted) begin
            case (state)
                3'h0: begin // Fetch
                    opcode <= memory[pc[7:0]];
                    state <= 3'h1;
                end
                3'h1: begin // Execute
                    case (opcode)
                        8'h40: eax <= eax + 1; // INC EAX
                        8'h48: eax <= eax - 1; // DEC EAX
                        8'hF4: halted <= 1'b1; // HLT
                    endcase
                    if (opcode != 8'hF4) begin
                        pc <= pc + 1;
                        state <= 3'h0;
                    end
                end
            endcase
        end
    end

endmodule

module tb_demo;
    reg clk, rst_n;
    wire [31:0] pc, eax;
    wire halted;
    
    cix32_demo dut(clk, rst_n, pc, eax, halted);
    
    initial begin
        clk = 0;
        forever #5 clk = ~clk;
    end
    
    initial begin
        rst_n = 0;
        #20 rst_n = 1;
        
        wait(halted);
        #20;
        
        $display("CIX-32 Demo Results:");
        $display("Final PC: 0x%08h", pc);
        $display("Final EAX: 0x%08h", eax);
        $display("Expected EAX: 0x00000002");
        
        if (eax == 32'h2) $display("✅ TEST PASSED");
        else $display("❌ TEST FAILED");
        
        $finish;
    end
    
    initial begin
        $dumpfile("cix32_demo.vcd");
        $dumpvars(0, tb_demo);
    end

endmodule

demo/cix32_demo.vcd
$date
	Thu Aug 14 19:51:44 2025
$end
$version
	Icarus Verilog
$end
$timescale
	1s
$end
$scope module tb_demo $end
$var wire 32 ! pc [31:0] $end
$var wire 1 " halted $end
$var wire 32 # eax [31:0] $end
$var reg 1 $ clk $end
$var reg 1 % rst_n $end
$scope module dut $end
$var wire 1 $ clk $end
$var wire 1 % rst_n $end
$var reg 32 & eax [31:0] $end
$var reg 1 " halted $end
$var reg 8 ' opcode [7:0] $end
$var reg 32 ( pc [31:0] $end
$var reg 3 ) state [2:0] $end
$upscope $end
$upscope $end
$enddefinitions $end
$comment Show the parameter values. $end
$dumpall
$end
#0
$dumpvars
b0 )
b0 (
bx '
b0 &
0%
0$
b0 #
0"
b0 !
$end
#5
1$
#10
0$
#15
1$
#20
0$
1%
#25
b1 )
b1000000 '
1$
#30
0$
#35
b0 )
b1 !
b1 (
b1 #
b1 &
1$
#40
0$
#45
b1 )
1$
#50
0$
#55
b0 )
b10 !
b10 (
b10 #
b10 &
1$
#60
0$
#65
b1 )
b1001000 '
1$
#70
0$
#75
b0 )
b11 !
b11 (
b1 #
b1 &
1$
#80
0$
#85
b1 )
b1000000 '
1$
#90
0$
#95
b0 )
b100 !
b100 (
b10 #
b10 &
1$
#100
0$
#105
b1 )
b11110100 '
1$
#110
0$
#115
1"
1$
